YamlTagExtensions/__init__.py
YamlTagExtensions/core.py
YamlTagExtensions/file_loader.py
YamlTagExtensions/j2_loader.py
YamlTagExtensions/variable_loader.py
test/__init__.py
test/test_file_loader.py
test/test_j2_loader.py
test/test_variable_loader.py
test/test_yte_functionality.py
yte/__init__.py
yte/core.py
yte/file_loader.py
yte/j2_loader.py
yte/variable_loader.py
yaml_tag_extension-0.0.3.dist-info/METADATA
yaml_tag_extension-0.0.3.dist-info/WHEEL
yaml_tag_extension-0.0.3.dist-info/top_level.txt
yaml_tag_extension-0.0.3.dist-info/RECORD
