Metadata-Version: 2.1
Name: yaml-tag-extension
Version: 0.0.3
Summary: Project with extended YAML functionality.
Home-page: https://github.com/nayak-swastik/yaml-tag-extensions
Author: Swastik.Nayak
Author-email: swastik.nayak.eu@gmail.com
Requires-Dist: PyYAML >=6.0.2
Requires-Dist: smart-open >=7.0.4
Requires-Dist: jinja2 >=3.1.4
